setup.py
upyun_django/__init__.py
upyun_django/manage.py
upyun_django/test.py
upyun_django.egg-info/PKG-INFO
upyun_django.egg-info/SOURCES.txt
upyun_django.egg-info/dependency_links.txt
upyun_django.egg-info/requires.txt
upyun_django.egg-info/top_level.txt
upyun_django/storage/__init__.py
upyun_django/storage/fields.py
upyun_django/storage/models.py
upyun_django/storage/storage.py
upyun_django/storage/test.py
upyun_django/storage/urls.py
upyun_django/storage/utils.py
upyun_django/storage/migrations/0001_initial.py
upyun_django/storage/migrations/__init__.py
upyun_django/upyun/__init__.py
upyun_django/upyun/settings.py
upyun_django/upyun/urls.py
upyun_django/upyun/wsgi.py