Metadata-Version: 1.1
Name: upyun-django
Version: 0.0.2
Summary: django upyun support
Home-page: http://bruceshi.me
Author: bruceshi
Author-email: shibocuhk@gmail.com
License: MIT
Platform: UNKNOWN
Classifier: Development Status :: 3 - Alpha
Classifier: Intended Audience :: Developers
Classifier: Topic :: Utilities
Classifier: License :: OSI Approved :: MIT License
Classifier: Programming Language :: Python :: 2.7
Classifier: Operating System :: OS Independent
